spendpoint/__init__.py
spendpoint/__main__.py
spendpoint/bridge.py
spendpoint/configuration.py
spendpoint/endpoint.py
spendpoint/main.py
spendpoint/router.py
spendpoint/service.py
spendpoint-0.5.1.dist-info/LICENSE
spendpoint-0.5.1.dist-info/WHEEL
spendpoint-0.5.1.dist-info/METADATA
spendpoint-0.5.1.dist-info/RECORD
