Metadata-Version: 2.1
Name: spendpoint
Version: 0.5.1
Summary: SPARQL endpoint for ontologies.
Keywords: spendpoint
Author-email: Arkadiusz Michał Ryś <Arkadiusz.Michal.Rys@gmail.com>
Requires-Python: >=3.9
Classifier: License :: OSI Approved :: MIT License
Classifier: Programming Language :: Python :: 3
Classifier: Development Status :: 2 - Pre-Alpha
Classifier: Intended Audience :: Developers
Classifier: Natural Language :: English
Requires-Dist: toml~=0.10.2
Requires-Dist: arklog~=0.5.1
Requires-Dist: rdflib~=7.0.0
Requires-Dist: pandas~=2.0.1
Requires-Dist: dacite~=1.8.1
Requires-Dist: fastapi~=0.101.1
Requires-Dist: pyarrow~=12.0.1
Requires-Dist: requests~=2.31.0
Requires-Dist: starlette<=0.28.0
Requires-Dist: python-magic~=0.4.27
Requires-Dist: uvicorn[standard]~=0.23.2
Requires-Dist: tox~=4.6.4 ; extra == "dev"
Requires-Dist: pip~=23.2.1 ; extra == "dev"
Requires-Dist: flit~=3.9.0 ; extra == "dev"
Requires-Dist: twine~=4.0.2 ; extra == "dev"
Requires-Dist: numpy~=1.25.2 ; extra == "dev"
Requires-Dist: invoke~=2.2.0 ; extra == "dev"
Requires-Dist: jinja2~=3.1.2 ; extra == "dev"
Requires-Dist: flake8~=6.1.0 ; extra == "dev"
Requires-Dist: coverage~=7.2.7 ; extra == "dev"
Requires-Dist: sphinx~=7.1.2 ; extra == "doc"
Requires-Dist: pytest~=7.4.0 ; extra == "test"
Requires-Dist: sparqlwrapper~=2.0.0 ; extra == "test"
Project-URL: source, https://git.rys.one/dtdesign/spendpoint
Provides-Extra: dev
Provides-Extra: doc
Provides-Extra: test
